O1/iiitb_counter.v
module bcd(RN,CK,Qz,Qu,Q);
input RN,CK;
output [3:0] Qz;
output [3:0] Qu;
output [7:0] Q;
reg  [3:0] Qz1,Qu1;

always @ (posedge CK or negedge RN)
begin
if(!RN )   begin
           Qz1=4'b0;
           Qu1=4'b0;
           end
else
begin
    if ({Qz1,Qu1}==8'b10011001) 
    begin
      Qz1=4'b0;
      Qu1=4'b0;
    end
    else if  (Qu1==4'b1001) begin
      Qu1=4'b0;
      Qz1= Qz1 +1;

      if(Qz1==4'b1001)
          Qz1=4'b0;
      end
    else
      Qu1=Qu1+1;
end
end

assign Q={Qz1,Qu1};
assign Qu=Qu1;
assign Qz=Qz1;

endmodule


// module up_counter    (
// out     ,  // Output of the counter
// enable  ,  // enable for counter
// clk     ,  // clock Input
// reset      // reset Input
// );
// //----------Output Ports--------------
//     output [7:0] out;
// //------------Input Ports--------------
//      input enable, clk, reset;
// //------------Internal Variables--------
//     reg [7:0] out;
// //-------------Code Starts Here-------
// always @(posedge clk)
// if (reset) begin
//   out <= 8'b0 ;
// end else if (enable) begin
//   out <= out + 1;
// end


// endmodule

iiitb_counter_tb.v
`include "iiitb_counter.v"
module test_bcd();
reg aRN,aCK;
wire [7:0] aQ;
wire [3:0] aQu,aQz;

bcd test_bcd(.RN(aRN),.CK(aCK),.Qu(aQu),.Qz(aQz),.Q(aQ));

initial begin

$dumpfile("iiitb_counter_tb.vcd");
$dumpvars(0, test_bcd);

aRN=1'b0;
aCK=1'b1;

#5 aRN=1'b1;
#300 $finish;
end

always #3 aCK = ~aCK;
endmodule

O1/iiitb_counter_tb.vcd
$date
	Tue Aug 16 13:09:25 2022
$end
$version
	Icarus Verilog
$end
$timescale
	1s
$end
$scope module test_bcd $end
$scope module test_bcd $end
$var wire 1 ! CK $end
$var wire 4 " Qu [3:0] $end
$var wire 4 # Qz [3:0] $end
$var wire 1 $ RN $end
$var wire 8 % Q [7:0] $end
$var reg 4 & Qu1 [3:0] $end
$var reg 4 ' Qz1 [3:0] $end
$upscope $end
$upscope $end
$enddefinitions $end
#0
$dumpvars
b0 '
b0 &
b0 %
0$
b0 #
b0 "
1!
$end
#3
0!
#5
1$
#6
b1 %
b1 "
b1 &
1!
#9
0!
#12
b10 %
b10 "
b10 &
1!
#15
0!
#18
b11 %
b11 "
b11 &
1!
#21
0!
#24
b100 %
b100 "
b100 &
1!
#27
0!
#30
b101 %
b101 "
b101 &
1!
#33
0!
#36
b110 %
b110 "
b110 &
1!
#39
0!
#42
b111 %
b111 "
b111 &
1!
#45
0!
#48
b1000 %
b1000 "
b1000 &
1!
#51
0!
#54
b1001 %
b1001 "
b1001 &
1!
#57
0!
#60
b1 #
b1 '
b10000 %
b0 "
b0 &
1!
#63
0!
#66
b10001 %
b1 "
b1 &
1!
#69
0!
#72
b10010 %
b10 "
b10 &
1!
#75
0!
#78
b10011 %
b11 "
b11 &
1!
#81
0!
#84
b10100 %
b100 "
b100 &
1!
#87
0!
#90
b10101 %
b101 "
b101 &
1!
#93
0!
#96
b10110 %
b110 "
b110 &
1!
#99
0!
#102
b10111 %
b111 "
b111 &
1!
#105
0!
#108
b11000 %
b1000 "
b1000 &
1!
#111
0!
#114
b11001 %
b1001 "
b1001 &
1!
#117
0!
#120
b10 #
b10 '
b100000 %
b0 "
b0 &
1!
#123
0!
#126
b100001 %
b1 "
b1 &
1!
#129
0!
#132
b100010 %
b10 "
b10 &
1!
#135
0!
#138
b100011 %
b11 "
b11 &
1!
#141
0!
#144
b100100 %
b100 "
b100 &
1!
#147
0!
#150
b100101 %
b101 "
b101 &
1!
#153
0!
#156
b100110 %
b110 "
b110 &
1!
#159
0!
#162
b100111 %
b111 "
b111 &
1!
#165
0!
#168
b101000 %
b1000 "
b1000 &
1!
#171
0!
#174
b101001 %
b1001 "
b1001 &
1!
#177
0!
#180
b11 #
b11 '
b110000 %
b0 "
b0 &
1!
#183
0!
#186
b110001 %
b1 "
b1 &
1!
#189
0!
#192
b110010 %
b10 "
b10 &
1!
#195
0!
#198
b110011 %
b11 "
b11 &
1!
#201
0!
#204
b110100 %
b100 "
b100 &
1!
#207
0!
#210
b110101 %
b101 "
b101 &
1!
#213
0!
#216
b110110 %
b110 "
b110 &
1!
#219
0!
#222
b110111 %
b111 "
b111 &
1!
#225
0!
#228
b111000 %
b1000 "
b1000 &
1!
#231
0!
#234
b111001 %
b1001 "
b1001 &
1!
#237
0!
#240
b100 #
b100 '
b1000000 %
b0 "
b0 &
1!
#243
0!
#246
b1000001 %
b1 "
b1 &
1!
#249
0!
#252
b1000010 %
b10 "
b10 &
1!
#255
0!
#258
b1000011 %
b11 "
b11 &
1!
#261
0!
#264
b1000100 %
b100 "
b100 &
1!
#267
0!
#270
b1000101 %
b101 "
b101 &
1!
#273
0!
#276
b1000110 %
b110 "
b110 &
1!
#279
0!
#282
b1000111 %
b111 "
b111 &
1!
#285
0!
#288
b1001000 %
b1000 "
b1000 &
1!
#291
0!
#294
b1001001 %
b1001 "
b1001 &
1!
#297
0!
#300
b101 #
b101 '
b1010000 %
b0 "
b0 &
1!
